harfbuzz.py
HarfPy-0.9.dist-info/COPYING
HarfPy-0.9.dist-info/METADATA
HarfPy-0.9.dist-info/WHEEL
HarfPy-0.9.dist-info/top_level.txt
HarfPy-0.9.dist-info/RECORD
