Metadata-Version: 2.1
Name: HarfPy
Version: 0.9
Summary: language bindings for HarfBuzz
Home-page: https://github.com/ldo/harfpy
Author: Lawrence D'Oliveiro
Author-email: ldo@geek-central.gen.nz
License: LGPL v2.1+
Platform: Linux
Classifier: Programming Language :: Python :: 3.3
Classifier: Development Status :: 4 - Beta
Classifier: Intended Audience :: Developers
Classifier: License :: OSI Approved :: GNU Library or Lesser General Public License (LGPL)
Classifier: Operating System :: POSIX :: Linux
Classifier: Topic :: Software Development :: Libraries
Classifier: Topic :: Text Processing :: Fonts
